cardea/__init__.py
cardea/core.py
cardea/benchmark/__init__.py
cardea/benchmark/benchmark.py
cardea/benchmark/benchmark_cli.py
cardea/benchmark/task.py
cardea/data_loader/__init__.py
cardea/data_loader/data_loader.py
cardea/data_loader/entityset_loader.py
cardea/data_loader/load_mimic.py
cardea/data_loader/schema.xml
cardea/featurization/__init__.py
cardea/featurization/featurization.py
cardea/fhir/Account.py
cardea/fhir/ActivityDefinition.py
cardea/fhir/Address.py
cardea/fhir/AdverseEvent.py
cardea/fhir/Age.py
cardea/fhir/AllergyIntolerance.py
cardea/fhir/Annotation.py
cardea/fhir/Appointment.py
cardea/fhir/AppointmentResponse.py
cardea/fhir/Attachment.py
cardea/fhir/AuditEvent.py
cardea/fhir/BackboneElement.py
cardea/fhir/Basic.py
cardea/fhir/Binary.py
cardea/fhir/BodySite.py
cardea/fhir/Bundle.py
cardea/fhir/CapabilityStatement.py
cardea/fhir/CarePlan.py
cardea/fhir/CareTeam.py
cardea/fhir/ChargeItem.py
cardea/fhir/Claim.py
cardea/fhir/ClaimResponse.py
cardea/fhir/ClinicalImpression.py
cardea/fhir/CodeSystem.py
cardea/fhir/CodeableConcept.py
cardea/fhir/Coding.py
cardea/fhir/Communication.py
cardea/fhir/CommunicationRequest.py
cardea/fhir/CompartmentDefinition.py
cardea/fhir/Composition.py
cardea/fhir/ConceptMap.py
cardea/fhir/Condition.py
cardea/fhir/Consent.py
cardea/fhir/ContactDetail.py
cardea/fhir/ContactPoint.py
cardea/fhir/Contract.py
cardea/fhir/Contributor.py
cardea/fhir/Count.py
cardea/fhir/Coverage.py
cardea/fhir/DataElement.py
cardea/fhir/DataRequirement.py
cardea/fhir/DetectedIssue.py
cardea/fhir/Device.py
cardea/fhir/DeviceComponent.py
cardea/fhir/DeviceMetric.py
cardea/fhir/DeviceRequest.py
cardea/fhir/DeviceUseStatement.py
cardea/fhir/DiagnosticReport.py
cardea/fhir/Distance.py
cardea/fhir/DocumentManifest.py
cardea/fhir/DocumentReference.py
cardea/fhir/DomainResource.py
cardea/fhir/Dosage.py
cardea/fhir/Duration.py
cardea/fhir/Element.py
cardea/fhir/ElementDefinition.py
cardea/fhir/EligibilityRequest.py
cardea/fhir/EligibilityResponse.py
cardea-0.1.2.dist-info/AUTHORS.rst
cardea-0.1.2.dist-info/LICENSE
cardea-0.1.2.dist-info/METADATA
cardea-0.1.2.dist-info/WHEEL
cardea-0.1.2.dist-info/entry_points.txt
cardea-0.1.2.dist-info/top_level.txt
cardea-0.1.2.dist-info/RECORD
