Metadata-Version: 2.1
Name: cardea
Version: 0.1.2
Summary: Cardea
Home-page: https://github.com/MLBazaar/Cardea
Author: MIT Data To AI Lab
Author-email: dailabmit@gmail.com
License: MIT license
Keywords: cardea
Platform: UNKNOWN
Classifier: Development Status :: 2 - Pre-Alpha
Classifier: Intended Audience :: Developers
Classifier: License :: OSI Approved :: MIT License
Classifier: Natural Language :: English
Classifier: Programming Language :: Python :: 3
Classifier: Programming Language :: Python :: 3.4
Classifier: Programming Language :: Python :: 3.5
Classifier: Programming Language :: Python :: 3.6
Requires-Python: >=3.4
Requires-Dist: mlblocks (<0.5,>=0.4.0)
Requires-Dist: mlprimitives (<0.4,>=0.3.0)
Requires-Dist: baytune (<0.5,>=0.4.0)
Requires-Dist: pyCLI (==2.0.3)
Requires-Dist: scikit-learn (<0.22,>=0.21)
Requires-Dist: featuretools (<0.25,>=0.20.0)
Provides-Extra: dev
Requires-Dist: bumpversion (>=0.5.3) ; extra == 'dev'
Requires-Dist: pip (>=9.0.1) ; extra == 'dev'
Requires-Dist: watchdog (>=0.8.3) ; extra == 'dev'
Requires-Dist: m2r2 (<0.3,>=0.2.5) ; extra == 'dev'
Requires-Dist: nbsphinx (<0.7,>=0.5.0) ; extra == 'dev'
Requires-Dist: Sphinx (<3.3,>=3) ; extra == 'dev'
Requires-Dist: pydata-sphinx-theme ; extra == 'dev'
Requires-Dist: autodocsumm (<1,>=0.1.10) ; extra == 'dev'
Requires-Dist: ipython (<7.5,>=6.5) ; extra == 'dev'
Requires-Dist: flake8 (<4,>=3.7.7) ; extra == 'dev'
Requires-Dist: isort (<5,>=4.3.4) ; extra == 'dev'
Requires-Dist: autoflake (<2,>=1.3) ; extra == 'dev'
Requires-Dist: autopep8 (<2,>=1.3.5) ; extra == 'dev'
Requires-Dist: twine (>=1.10.0) ; extra == 'dev'
Requires-Dist: wheel (>=0.30.0) ; extra == 'dev'
Requires-Dist: tox (>=2.9.1) ; extra == 'dev'
Requires-Dist: coverage (>=4.5.1) ; extra == 'dev'
Requires-Dist: pytest (>=3.4.2) ; extra == 'dev'
Requires-Dist: pytest-cov (>=2.6.0) ; extra == 'dev'
Requires-Dist: rundoc (<0.5,>=0.4.3) ; extra == 'dev'
Provides-Extra: test
Requires-Dist: pytest (>=3.4.2) ; extra == 'test'
Requires-Dist: pytest-cov (>=2.6.0) ; extra == 'test'
Requires-Dist: rundoc (<0.5,>=0.4.3) ; extra == 'test'
